{
  "results_found": 3201,
  "results_start": 80,
  "results_shown": 20,
  "restaurants": [
    {
      "restaurant": {
        "R": {
          "res_id": 16588532,
          "is_grocery_store": false,
          "has_menu_status": {
            "delivery": -1,
            "takeaway": -1
          }
        },
        "apikey": "c1d331ff7e4dcfb200d33fa7efb9b184",
        "id": "16588532",
        "name": "Thai By 3 Monkeys",
        "url": "https:\/\/www.zomato.com\/adelaide\/thai-by-3-monkeys-north-adelaide?utm_source=api_basic_user&utm_medium=api&utm_campaign=v2.1",
        "location": {
          "address": "33 O'Connell Street, North Adelaide, Adelaide",
          "locality": "O'connell Street, North Adelaide",
          "city": "Adelaide",
          "city_id": 297,
          "latitude": "-34.9081805556",
          "longitude": "138.5966805556",
          "zipcode": "5006",
          "country_id": 14,
          "locality_verbose": "O'connell Street, North Adelaide, Adelaide, SA"
        },
        "switch_to_order_menu": 0,
        "cuisines": "Thai",
        "timings": "Closed (Mon),5:30 PM to 10 PM (Tue, Wed, Sat, Sun), 12 Noon to 2:30 PM, 5:30 PM to 10 PM (Thu-Fri)",
        "average_cost_for_two": 60,
        "price_range": 3,
        "currency": "$",
        "highlights": [
          "Dinner",
          "Takeaway Available",
          "Lunch",
          "Outdoor Seating",
          "Vegetarian Friendly",
          "BYO"
        ],
        "offers": [],
        "opentable_support": 0,
        "is_zomato_book_res": 0,
        "mezzo_provider": "OTHER",
        "is_book_form_web_view": 0,
        "book_form_web_view_url": "",
        "book_again_url": "",
        "thumb": "https:\/\/b.zmtcdn.com\/data\/res_imagery\/16588532_RESTAURANT_bec63357212aa8f258130d1508dd3bc8_c.jpg?fit=around%7C200%3A200&crop=200%3A200%3B%2A%2C%2A",
        "user_rating": {
          "aggregate_rating": "4.4",
          "rating_text": "Very Good",
          "rating_color": "5BA829",
          "rating_obj": {
            "title": {
              "text": "4.4"
            },
            "bg_color": {
              "type": "lime",
              "tint": "700"
            }
          },
          "votes": 222
        },
        "all_reviews_count": 83,
        "photos_url": "https:\/\/www.zomato.com\/adelaide\/thai-by-3-monkeys-north-adelaide\/photos?utm_source=api_basic_user&utm_medium=api&utm_campaign=v2.1#tabtop",
        "photo_count": 64,
        "menu_url": "https:\/\/www.zomato.com\/adelaide\/thai-by-3-monkeys-north-adelaide\/menu?utm_source=api_basic_user&utm_medium=api&utm_campaign=v2.1&openSwipeBox=menu&showMinimal=1#tabtop",
        "featured_image": "https:\/\/b.zmtcdn.com\/data\/res_imagery\/16588532_RESTAURANT_bec63357212aa8f258130d1508dd3bc8_c.jpg",
        "medio_provider": false,
        "has_online_delivery": 0,
        "is_delivering_now": 0,
        "store_type": "",
        "include_bogo_offers": true,
        "deeplink": "zomato:\/\/restaurant\/16588532",
        "is_table_reservation_supported": 0,
        "has_table_booking": 0,
        "events_url": "https:\/\/www.zomato.com\/adelaide\/thai-by-3-monkeys-north-adelaide\/events#tabtop?utm_source=api_basic_user&utm_medium=api&utm_campaign=v2.1",
        "phone_numbers": "(08) 8267 3188",
        "all_reviews": {
          "reviews": [
            {
              "review": []
            },
            {
              "review": []
            },
            {
              "review": []
            },
            {
              "review": []
            },
            {
              "review": []
            }
          ]
        },
        "establishment": [
          "Casual Dining"
        ],
        "establishment_types": []
      }
    },
    {
      "restaurant": {
        "R": {
          "res_id": 16587020,
          "is_grocery_store": false,
          "has_menu_status": {
            "delivery": -1,
            "takeaway": -1
          }
        },
        "apikey": "c1d331ff7e4dcfb200d33fa7efb9b184",
        "id": "16587020",
        "name": "The Lion Hotel",
        "url": "https:\/\/www.zomato.com\/adelaide\/the-lion-hotel-north-adelaide?utm_source=api_basic_user&utm_medium=api&utm_campaign=v2.1",
        "location": {
          "address": "161 Melbourne Street, North Adelaide, Adelaide",
          "locality": "Melbourne Street, North Adelaide",
          "city": "Adelaide",
          "city_id": 297,
          "latitude": "-34.9079445225",
          "longitude": "138.6058836803",
          "zipcode": "5006",
          "country_id": 14,
          "locality_verbose": "Melbourne Street, North Adelaide, Adelaide, SA"
        },
        "switch_to_order_menu": 0,
        "cuisines": "Modern Australian, Pub Food",
        "timings": "7:30 AM to 12 Midnight (Mon-Sun)",
        "average_cost_for_two": 80,
        "price_range": 3,
        "currency": "$",
        "highlights": [
          "Dinner",
          "Credit Card",
          "Takeaway Available",
          "Lunch",
          "Cash",
          "Delivery",
          "Breakfast",
          "Lunch Menu",
          "Fullbar",
          "Live Music",
          "Kid Friendly",
          "Wifi",
          "Vegetarian Friendly",
          "Nightlife",
          "Table booking recommended",
          "Outdoor Seating",
          "Smoking Area",
          "Gluten Free Options"
        ],
        "offers": [],
        "opentable_support": 0,
        "is_zomato_book_res": 0,
        "mezzo_provider": "OTHER",
        "is_book_form_web_view": 0,
        "book_form_web_view_url": "",
        "book_again_url": "",
        "thumb": "https:\/\/b.zmtcdn.com\/data\/res_imagery\/16587020_RESTAURANT_72384149a8ff54d0e5b930a83d23253a_c.JPG?fit=around%7C200%3A200&crop=200%3A200%3B%2A%2C%2A",
        "user_rating": {
          "aggregate_rating": "4.1",
          "rating_text": "Very Good",
          "rating_color": "5BA829",
          "rating_obj": {
            "title": {
              "text": "4.1"
            },
            "bg_color": {
              "type": "lime",
              "tint": "700"
            }
          },
          "votes": 305
        },
        "all_reviews_count": 117,
        "photos_url": "https:\/\/www.zomato.com\/adelaide\/the-lion-hotel-north-adelaide\/photos?utm_source=api_basic_user&utm_medium=api&utm_campaign=v2.1#tabtop",
        "photo_count": 125,
        "menu_url": "https:\/\/www.zomato.com\/adelaide\/the-lion-hotel-north-adelaide\/menu?utm_source=api_basic_user&utm_medium=api&utm_campaign=v2.1&openSwipeBox=menu&showMinimal=1#tabtop",
        "featured_image": "https:\/\/b.zmtcdn.com\/data\/res_imagery\/16587020_RESTAURANT_72384149a8ff54d0e5b930a83d23253a_c.JPG",
        "medio_provider": false,
        "has_online_delivery": 0,
        "is_delivering_now": 0,
        "store_type": "",
        "include_bogo_offers": true,
        "deeplink": "zomato:\/\/restaurant\/16587020",
        "is_table_reservation_supported": 0,
        "has_table_booking": 0,
        "events_url": "https:\/\/www.zomato.com\/adelaide\/the-lion-hotel-north-adelaide\/events#tabtop?utm_source=api_basic_user&utm_medium=api&utm_campaign=v2.1",
        "phone_numbers": "08 8367 0222",
        "all_reviews": {
          "reviews": [
            {
              "review": []
            },
            {
              "review": []
            },
            {
              "review": []
            },
            {
              "review": []
            },
            {
              "review": []
            }
          ]
        },
        "establishment": [
          "Pub"
        ],
        "establishment_types": []
      }
    },
    {
      "restaurant": {
        "R": {
          "res_id": 16587524,
          "is_grocery_store": false,
          "has_menu_status": {
            "delivery": -1,
            "takeaway": -1
          }
        },
        "apikey": "c1d331ff7e4dcfb200d33fa7efb9b184",
        "id": "16587524",
        "name": "Addis Ababa Cafe",
        "url": "https:\/\/www.zomato.com\/adelaide\/addis-ababa-cafe-west-hindmarsh?utm_source=api_basic_user&utm_medium=api&utm_campaign=v2.1",
        "location": {
          "address": "4\/462 Port Road, West Hindmarsh, Adelaide",
          "locality": "Port Road, West Hindmarsh",
          "city": "Adelaide",
          "city_id": 297,
          "latitude": "-34.8992540000",
          "longitude": "138.5623170000",
          "zipcode": "5007",
          "country_id": 14,
          "locality_verbose": "Port Road, West Hindmarsh, Adelaide, SA"
        },
        "switch_to_order_menu": 0,
        "cuisines": "African, Ethiopian",
        "timings": "5:30 PM to 9 PM (Mon, Tue, Thu, Sun), Closed (Wed),5:30 PM to 10 PM (Fri-Sat)",
        "average_cost_for_two": 60,
        "price_range": 3,
        "currency": "$",
        "highlights": [
          "No Alcohol Available",
          "Takeaway Available",
          "Dinner",
          "Cash",
          "Outdoor Seating",
          "Table booking recommended",
          "Vegetarian Friendly",
          "Indoor Seating",
          "Vegan Options"
        ],
        "offers": [],
        "opentable_support": 0,
        "is_zomato_book_res": 0,
        "mezzo_provider": "OTHER",
        "is_book_form_web_view": 0,
        "book_form_web_view_url": "",
        "book_again_url": "",
        "thumb": "https:\/\/b.zmtcdn.com\/data\/res_imagery\/16587524_RESTAURANT_3af5e2c0245b2d2e9a716d3f5bde34d7_c.jpg?fit=around%7C200%3A200&crop=200%3A200%3B%2A%2C%2A",
        "user_rating": {
          "aggregate_rating": "4.4",
          "rating_text": "Very Good",
          "rating_color": "5BA829",
          "rating_obj": {
            "title": {
              "text": "4.4"
            },
            "bg_color": {
              "type": "lime",
              "tint": "700"
            }
          },
          "votes": 213
        },
        "all_reviews_count": 73,
        "photos_url": "https:\/\/www.zomato.com\/adelaide\/addis-ababa-cafe-west-hindmarsh\/photos?utm_source=api_basic_user&utm_medium=api&utm_campaign=v2.1#tabtop",
        "photo_count": 40,
        "menu_url": "https:\/\/www.zomato.com\/adelaide\/addis-ababa-cafe-west-hindmarsh\/menu?utm_source=api_basic_user&utm_medium=api&utm_campaign=v2.1&openSwipeBox=menu&showMinimal=1#tabtop",
        "featured_image": "https:\/\/b.zmtcdn.com\/data\/res_imagery\/16587524_RESTAURANT_3af5e2c0245b2d2e9a716d3f5bde34d7_c.jpg",
        "medio_provider": false,
        "has_online_delivery": 0,
        "is_delivering_now": 0,
        "store_type": "",
        "include_bogo_offers": true,
        "deeplink": "zomato:\/\/restaurant\/16587524",
        "is_table_reservation_supported": 0,
        "has_table_booking": 0,
        "events_url": "https:\/\/www.zomato.com\/adelaide\/addis-ababa-cafe-west-hindmarsh\/events#tabtop?utm_source=api_basic_user&utm_medium=api&utm_campaign=v2.1",
        "phone_numbers": "556406",
        "all_reviews": {
          "reviews": [
            {
              "review": []
            },
            {
              "review": []
            },
            {
              "review": []
            },
            {
              "review": []
            },
            {
              "review": []
            }
          ]
        },
        "establishment": [
          "Casual Dining"
        ],
        "establishment_types": []
      }
    },
    {
      "restaurant": {
        "R": {
          "res_id": 18282070,
          "is_grocery_store": false,
          "has_menu_status": {
            "delivery": -1,
            "takeaway": -1
          }
        },
        "apikey": "c1d331ff7e4dcfb200d33fa7efb9b184",
        "id": "18282070",
        "name": "Gyoza Gyoza",
        "url": "https:\/\/www.zomato.com\/adelaide\/gyoza-gyoza-city-centre?utm_source=api_basic_user&utm_medium=api&utm_campaign=v2.1",
        "location": {
          "address": "95-97, Gouger Street, City Centre, Adelaide",
          "locality": "Gouger Street, City Centre",
          "city": "Adelaide",
          "city_id": 297,
          "latitude": "-34.9306170000",
          "longitude": "138.5935453000",
          "zipcode": "",
          "country_id": 14,
          "locality_verbose": "Gouger Street, City Centre, Adelaide, SA"
        },
        "switch_to_order_menu": 0,
        "cuisines": "Japanese",
        "timings": "11:30AM to 10:30PM (Mon, Tue, Wed, Thu, Sun), 11:30AM to 12Midnight (Fri-Sat)",
        "average_cost_for_two": 35,
        "price_range": 2,
        "currency": "$",
        "highlights": [
          "Cash",
          "Debit Card",
          "Delivery",
          "Dinner",
          "Credit Card",
          "Takeaway Available",
          "Lunch",
          "Indoor Seating",
          "Smoking Area",
          "Gluten Free Options",
          "Locally Sourced",
          "Wine",
          "Serves Cocktails",
          "Street Parking",
          "Available for Functions",
          "Outdoor Seating",
          "Kid Friendly",
          "Wheelchair Accessible",
          "Vegetarian Friendly",
          "Fullbar",
          "Beer"
        ],
        "offers": [],
        "opentable_support": 0,
        "is_zomato_book_res": 0,
        "mezzo_provider": "OTHER",
        "is_book_form_web_view": 0,
        "book_form_web_view_url": "",
        "book_again_url": "",
        "thumb": "https:\/\/b.zmtcdn.com\/data\/res_imagery\/18282070_RESTAURANT_137610b98c1dbec59d2f8eaef7a0e792.png?fit=around%7C200%3A200&crop=200%3A200%3B%2A%2C%2A",
        "user_rating": {
          "aggregate_rating": "3.6",
          "rating_text": "Good",
          "rating_color": "9ACD32",
          "rating_obj": {
            "title": {
              "text": "3.6"
            },
            "bg_color": {
              "type": "lime",
              "tint": "600"
            }
          },
          "votes": 176
        },
        "all_reviews_count": 110,
        "photos_url": "https:\/\/www.zomato.com\/adelaide\/gyoza-gyoza-city-centre\/photos?utm_source=api_basic_user&utm_medium=api&utm_campaign=v2.1#tabtop",
        "photo_count": 191,
        "menu_url": "https:\/\/www.zomato.com\/adelaide\/gyoza-gyoza-city-centre\/menu?utm_source=api_basic_user&utm_medium=api&utm_campaign=v2.1&openSwipeBox=menu&showMinimal=1#tabtop",
        "featured_image": "https:\/\/b.zmtcdn.com\/data\/res_imagery\/18282070_RESTAURANT_137610b98c1dbec59d2f8eaef7a0e792.png",
        "medio_provider": false,
        "has_online_delivery": 0,
        "is_delivering_now": 0,
        "store_type": "",
        "include_bogo_offers": true,
        "deeplink": "zomato:\/\/restaurant\/18282070",
        "is_table_reservation_supported": 0,
        "has_table_booking": 0,
        "events_url": "https:\/\/www.zomato.com\/adelaide\/gyoza-gyoza-city-centre\/events#tabtop?utm_source=api_basic_user&utm_medium=api&utm_campaign=v2.1",
        "phone_numbers": "08 7226 8983",
        "all_reviews": {
          "reviews": [
            {
              "review": []
            },
            {
              "review": []
            },
            {
              "review": []
            },
            {
              "review": []
            },
            {
              "review": []
            }
          ]
        },
        "establishment": [
          "Casual Dining"
        ],
        "establishment_types": []
      }
    },
    {
      "restaurant": {
        "R": {
          "res_id": 16587731,
          "is_grocery_store": false,
          "has_menu_status": {
            "delivery": -1,
            "takeaway": -1
          }
        },
        "apikey": "c1d331ff7e4dcfb200d33fa7efb9b184",
        "id": "16587731",
        "name": "Melt CBD",
        "url": "https:\/\/www.zomato.com\/adelaide\/melt-cbd-city-centre?utm_source=api_basic_user&utm_medium=api&utm_campaign=v2.1",
        "location": {
          "address": "38 Waymouth Street, Adelaide",
          "locality": "Waymouth Street, City Centre",
          "city": "Adelaide",
          "city_id": 297,
          "latitude": "-34.9259416667",
          "longitude": "138.5982972222",
          "zipcode": "5000",
          "country_id": 14,
          "locality_verbose": "Waymouth Street, City Centre, Adelaide, SA"
        },
        "switch_to_order_menu": 0,
        "cuisines": "Pizza, Tapas",
        "timings": "11 AM to 10 PM (Mon-Sat),Closed (Sun)",
        "average_cost_for_two": 60,
        "price_range": 3,
        "currency": "$",
        "highlights": [
          "Credit Card",
          "Lunch",
          "Takeaway Available",
          "Dinner",
          "Indoor Seating",
          "Wheelchair Accessible",
          "Gluten Free Options",
          "Vegetarian Friendly",
          "Outdoor Seating",
          "Smoking Area",
          "Halal",
          "Fullbar"
        ],
        "offers": [],
        "opentable_support": 0,
        "is_zomato_book_res": 0,
        "mezzo_provider": "OTHER",
        "is_book_form_web_view": 0,
        "book_form_web_view_url": "",
        "book_again_url": "",
        "thumb": "https:\/\/b.zmtcdn.com\/data\/res_imagery\/16587731_RESTAURANT_dfd1c7d567d4a292d8f7ed0e2ae04b90.jpg?fit=around%7C200%3A200&crop=200%3A200%3B%2A%2C%2A",
        "user_rating": {
          "aggregate_rating": "4.3",
          "rating_text": "Very Good",
          "rating_color": "5BA829",
          "rating_obj": {
            "title": {
              "text": "4.3"
            },
            "bg_color": {
              "type": "lime",
              "tint": "700"
            }
          },
          "votes": 390
        },
        "all_reviews_count": 124,
        "photos_url": "https:\/\/www.zomato.com\/adelaide\/melt-cbd-city-centre\/photos?utm_source=api_basic_user&utm_medium=api&utm_campaign=v2.1#tabtop",
        "photo_count": 68,
        "menu_url": "https:\/\/www.zomato.com\/adelaide\/melt-cbd-city-centre\/menu?utm_source=api_basic_user&utm_medium=api&utm_campaign=v2.1&openSwipeBox=menu&showMinimal=1#tabtop",
        "featured_image": "https:\/\/b.zmtcdn.com\/data\/res_imagery\/16587731_RESTAURANT_dfd1c7d567d4a292d8f7ed0e2ae04b90.jpg",
        "medio_provider": false,
        "has_online_delivery": 0,
        "is_delivering_now": 0,
        "store_type": "",
        "include_bogo_offers": true,
        "deeplink": "zomato:\/\/restaurant\/16587731",
        "is_table_reservation_supported": 0,
        "has_table_booking": 0,
        "events_url": "https:\/\/www.zomato.com\/adelaide\/melt-cbd-city-centre\/events#tabtop?utm_source=api_basic_user&utm_medium=api&utm_campaign=v2.1",
        "phone_numbers": "(08) 8211 6723",
        "all_reviews": {
          "reviews": [
            {
              "review": []
            },
            {
              "review": []
            },
            {
              "review": []
            },
            {
              "review": []
            },
            {
              "review": []
            }
          ]
        },
        "establishment": [
          "Casual Dining"
        ],
        "establishment_types": []
      }
    },
    {
      "restaurant": {
        "R": {
          "res_id": 16587696,
          "is_grocery_store": false,
          "has_menu_status": {
            "delivery": -1,
            "takeaway": -1
          }
        },
        "apikey": "c1d331ff7e4dcfb200d33fa7efb9b184",
        "id": "16587696",
        "name": "FB's Fancy Burgers",
        "url": "https:\/\/www.zomato.com\/adelaide\/fbs-fancy-burgers-blackwood?utm_source=api_basic_user&utm_medium=api&utm_campaign=v2.1",
        "location": {
          "address": "Shop 4, 237 Main Road, Blackwood",
          "locality": "Main Road, Blackwood",
          "city": "Adelaide",
          "city_id": 297,
          "latitude": "-35.0200388889",
          "longitude": "138.6165472222",
          "zipcode": "5051",
          "country_id": 14,
          "locality_verbose": "Main Road, Blackwood, Adelaide, SA"
        },
        "switch_to_order_menu": 0,
        "cuisines": "Burger",
        "timings": "11 AM to 9 PM (Mon-Sun)",
        "average_cost_for_two": 40,
        "price_range": 2,
        "currency": "$",
        "highlights": [
          "Credit Card",
          "Takeaway Available",
          "Lunch",
          "Dinner",
          "Indoor Seating",
          "Vegetarian Friendly",
          "Outdoor Seating",
          "Kid Friendly",
          "Gluten Free Options",
          "Beer"
        ],
        "offers": [],
        "opentable_support": 0,
        "is_zomato_book_res": 0,
        "mezzo_provider": "OTHER",
        "is_book_form_web_view": 0,
        "book_form_web_view_url": "",
        "book_again_url": "",
        "thumb": "https:\/\/b.zmtcdn.com\/data\/res_imagery\/16587696_RESTAURANT_280adce848c93694b2509f0077f7c539_c.jpg?fit=around%7C200%3A200&crop=200%3A200%3B%2A%2C%2A",
        "user_rating": {
          "aggregate_rating": "4.4",
          "rating_text": "Very Good",
          "rating_color": "5BA829",
          "rating_obj": {
            "title": {
              "text": "4.4"
            },
            "bg_color": {
              "type": "lime",
              "tint": "700"
            }
          },
          "votes": 372
        },
        "all_reviews_count": 120,
        "photos_url": "https:\/\/www.zomato.com\/adelaide\/fbs-fancy-burgers-blackwood\/photos?utm_source=api_basic_user&utm_medium=api&utm_campaign=v2.1#tabtop",
        "photo_count": 18,
        "menu_url": "https:\/\/www.zomato.com\/adelaide\/fbs-fancy-burgers-blackwood\/menu?utm_source=api_basic_user&utm_medium=api&utm_campaign=v2.1&openSwipeBox=menu&showMinimal=1#tabtop",
        "featured_image": "https:\/\/b.zmtcdn.com\/data\/res_imagery\/16587696_RESTAURANT_280adce848c93694b2509f0077f7c539_c.jpg",
        "medio_provider": false,
        "has_online_delivery": 0,
        "is_delivering_now": 0,
        "store_type": "",
        "include_bogo_offers": true,
        "deeplink": "zomato:\/\/restaurant\/16587696",
        "is_table_reservation_supported": 0,
        "has_table_booking": 0,
        "events_url": "https:\/\/www.zomato.com\/adelaide\/fbs-fancy-burgers-blackwood\/events#tabtop?utm_source=api_basic_user&utm_medium=api&utm_campaign=v2.1",
        "phone_numbers": "(08) 8370 0388",
        "all_reviews": {
          "reviews": [
            {
              "review": []
            },
            {
              "review": []
            },
            {
              "review": []
            },
            {
              "review": []
            },
            {
              "review": []
            }
          ]
        },
        "establishment": [
          "Casual Dining"
        ],
        "establishment_types": []
      }
    },
    {
      "restaurant": {
        "R": {
          "res_id": 17849698,
          "is_grocery_store": false,
          "has_menu_status": {
            "delivery": -1,
            "takeaway": -1
          }
        },
        "apikey": "c1d331ff7e4dcfb200d33fa7efb9b184",
        "id": "17849698",
        "name": "Gondola Gondola",
        "url": "https:\/\/www.zomato.com\/adelaide\/gondola-gondola-city-centre?utm_source=api_basic_user&utm_medium=api&utm_campaign=v2.1",
        "location": {
          "address": "1 Peel Street, Adelaide",
          "locality": "City Centre",
          "city": "Adelaide",
          "city_id": 297,
          "latitude": "-34.9230111111",
          "longitude": "138.5979166667",
          "zipcode": "5000",
          "country_id": 14,
          "locality_verbose": "City Centre"
        },
        "switch_to_order_menu": 0,
        "cuisines": "Vietnamese",
        "timings": "6 PM to 10 PM (Mon-Fri),6 PM to 2 AM (Sat),Closed (Sun)",
        "average_cost_for_two": 85,
        "price_range": 3,
        "currency": "$",
        "highlights": [
          "Cash",
          "Debit Card",
          "Takeaway Available",
          "Credit Card",
          "Dinner",
          "Vegetarian Friendly",
          "Indoor Seating",
          "Gluten Free Options",
          "Fullbar"
        ],
        "offers": [],
        "opentable_support": 0,
        "is_zomato_book_res": 0,
        "mezzo_provider": "OTHER",
        "is_book_form_web_view": 0,
        "book_form_web_view_url": "",
        "book_again_url": "",
        "thumb": "https:\/\/b.zmtcdn.com\/data\/res_imagery\/17849698_RESTAURANT_42dc61547b102bad742c8ffdaa9372f4_c.jpg?fit=around%7C200%3A200&crop=200%3A200%3B%2A%2C%2A",
        "user_rating": {
          "aggregate_rating": "3.9",
          "rating_text": "Good",
          "rating_color": "9ACD32",
          "rating_obj": {
            "title": {
              "text": "3.9"
            },
            "bg_color": {
              "type": "lime",
              "tint": "600"
            }
          },
          "votes": 116
        },
        "all_reviews_count": 65,
        "photos_url": "https:\/\/www.zomato.com\/adelaide\/gondola-gondola-city-centre\/photos?utm_source=api_basic_user&utm_medium=api&utm_campaign=v2.1#tabtop",
        "photo_count": 112,
        "menu_url": "https:\/\/www.zomato.com\/adelaide\/gondola-gondola-city-centre\/menu?utm_source=api_basic_user&utm_medium=api&utm_campaign=v2.1&openSwipeBox=menu&showMinimal=1#tabtop",
        "featured_image": "https:\/\/b.zmtcdn.com\/data\/res_imagery\/17849698_RESTAURANT_42dc61547b102bad742c8ffdaa9372f4_c.jpg",
        "medio_provider": false,
        "has_online_delivery": 0,
        "is_delivering_now": 0,
        "store_type": "",
        "include_bogo_offers": true,
        "deeplink": "zomato:\/\/restaurant\/17849698",
        "is_table_reservation_supported": 0,
        "has_table_booking": 0,
        "events_url": "https:\/\/www.zomato.com\/adelaide\/gondola-gondola-city-centre\/events#tabtop?utm_source=api_basic_user&utm_medium=api&utm_campaign=v2.1",
        "phone_numbers": "(08) 8123 3877",
        "all_reviews": {
          "reviews": [
            {
              "review": []
            },
            {
              "review": []
            },
            {
              "review": []
            },
            {
              "review": []
            },
            {
              "review": []
            }
          ]
        },
        "establishment": [
          "Casual Dining"
        ],
        "establishment_types": []
      }
    },
    {
      "restaurant": {
        "R": {
          "res_id": 16587024,
          "is_grocery_store": false,
          "has_menu_status": {
            "delivery": -1,
            "takeaway": -1
          }
        },
        "apikey": "c1d331ff7e4dcfb200d33fa7efb9b184",
        "id": "16587024",
        "name": "Lucia's Pizza and Spaghetti Bar",
        "url": "https:\/\/www.zomato.com\/adelaide\/lucias-pizza-and-spaghetti-bar-city-centre?utm_source=api_basic_user&utm_medium=api&utm_campaign=v2.1",
        "location": {
          "address": "Adelaide Central Markets, Shop 1, Gouger Street, Adelaide",
          "locality": "Gouger Street, City Centre",
          "city": "Adelaide",
          "city_id": 297,
          "latitude": "-34.9297722222",
          "longitude": "138.5971055556",
          "zipcode": "5000",
          "country_id": 14,
          "locality_verbose": "Gouger Street, City Centre, Adelaide, SA"
        },
        "switch_to_order_menu": 0,
        "cuisines": "Italian, Pizza, Coffee and Tea, Cafe Food",
        "timings": "7 AM to 4 PM (Mon-Thu),7 AM to 8:30 PM (Fri),7 AM to 2:30 PM (Sat),Closed (Sun)",
        "average_cost_for_two": 40,
        "price_range": 2,
        "currency": "$",
        "highlights": [
          "Cash",
          "Debit Card",
          "Lunch",
          "Credit Card",
          "Takeaway Available",
          "Breakfast",
          "Kid Friendly",
          "Vegetarian Friendly",
          "Wine",
          "Indoor Seating",
          "Beer"
        ],
        "offers": [],
        "opentable_support": 0,
        "is_zomato_book_res": 0,
        "mezzo_provider": "OTHER",
        "is_book_form_web_view": 0,
        "book_form_web_view_url": "",
        "book_again_url": "",
        "thumb": "https:\/\/b.zmtcdn.com\/data\/res_imagery\/16587024_RESTAURANT_13b0ec9d286e269aee8bd60155f08730.jpg?fit=around%7C200%3A200&crop=200%3A200%3B%2A%2C%2A",
        "user_rating": {
          "aggregate_rating": "4.2",
          "rating_text": "Very Good",
          "rating_color": "5BA829",
          "rating_obj": {
            "title": {
              "text": "4.2"
            },
            "bg_color": {
              "type": "lime",
              "tint": "700"
            }
          },
          "votes": 214
        },
        "all_reviews_count": 84,
        "photos_url": "https:\/\/www.zomato.com\/adelaide\/lucias-pizza-and-spaghetti-bar-city-centre\/photos?utm_source=api_basic_user&utm_medium=api&utm_campaign=v2.1#tabtop",
        "photo_count": 51,
        "menu_url": "https:\/\/www.zomato.com\/adelaide\/lucias-pizza-and-spaghetti-bar-city-centre\/menu?utm_source=api_basic_user&utm_medium=api&utm_campaign=v2.1&openSwipeBox=menu&showMinimal=1#tabtop",
        "featured_image": "https:\/\/b.zmtcdn.com\/data\/res_imagery\/16587024_RESTAURANT_13b0ec9d286e269aee8bd60155f08730.jpg",
        "medio_provider": false,
        "has_online_delivery": 0,
        "is_delivering_now": 0,
        "store_type": "",
        "include_bogo_offers": true,
        "deeplink": "zomato:\/\/restaurant\/16587024",
        "is_table_reservation_supported": 0,
        "has_table_booking": 0,
        "events_url": "https:\/\/www.zomato.com\/adelaide\/lucias-pizza-and-spaghetti-bar-city-centre\/events#tabtop?utm_source=api_basic_user&utm_medium=api&utm_campaign=v2.1",
        "phone_numbers": "(08) 8231 2303",
        "all_reviews": {
          "reviews": [
            {
              "review": []
            },
            {
              "review": []
            },
            {
              "review": []
            },
            {
              "review": []
            },
            {
              "review": []
            }
          ]
        },
        "establishment": [
          "Caf\u00e9"
        ],
        "establishment_types": []
      }
    },
    {
      "restaurant": {
        "R": {
          "res_id": 16589175,
          "is_grocery_store": false,
          "has_menu_status": {
            "delivery": -1,
            "takeaway": -1
          }
        },
        "apikey": "c1d331ff7e4dcfb200d33fa7efb9b184",
        "id": "16589175",
        "name": "Devour Cafe Patisserie",
        "url": "https:\/\/www.zomato.com\/adelaide\/devour-cafe-patisserie-hilton?utm_source=api_basic_user&utm_medium=api&utm_campaign=v2.1",
        "location": {
          "address": "52 Davenport Terrace, Hilton, Adelaide",
          "locality": "Hilton",
          "city": "Adelaide",
          "city_id": 297,
          "latitude": "-34.9342547412",
          "longitude": "138.5637659580",
          "zipcode": "5033",
          "country_id": 14,
          "locality_verbose": "Hilton"
        },
        "switch_to_order_menu": 0,
        "cuisines": "Desserts, Coffee and Tea, Cafe Food",
        "timings": "7 AM to 4 PM (Mon-Fri),8 AM to 2 PM (Sat-Sun)",
        "average_cost_for_two": 50,
        "price_range": 2,
        "currency": "$",
        "highlights": [
          "Cash",
          "Debit Card",
          "Lunch",
          "Credit Card",
          "Takeaway Available",
          "Breakfast",
          "No Alcohol Available",
          "Kid Friendly",
          "Wheelchair Accessible",
          "Gluten Free Options",
          "Vegetarian Friendly",
          "Desserts and Bakes",
          "Indoor Seating",
          "Vegan Options"
        ],
        "offers": [],
        "opentable_support": 0,
        "is_zomato_book_res": 0,
        "mezzo_provider": "OTHER",
        "is_book_form_web_view": 0,
        "book_form_web_view_url": "",
        "book_again_url": "",
        "thumb": "https:\/\/b.zmtcdn.com\/data\/res_imagery\/16589175_RESTAURANT_1a56f8cf406e4d65f3fe74d6408cfc5d.jpg?fit=around%7C200%3A200&crop=200%3A200%3B%2A%2C%2A",
        "user_rating": {
          "aggregate_rating": "4.0",
          "rating_text": "Very Good",
          "rating_color": "5BA829",
          "rating_obj": {
            "title": {
              "text": "4.0"
            },
            "bg_color": {
              "type": "lime",
              "tint": "600"
            }
          },
          "votes": 455
        },
        "all_reviews_count": 176,
        "photos_url": "https:\/\/www.zomato.com\/adelaide\/devour-cafe-patisserie-hilton\/photos?utm_source=api_basic_user&utm_medium=api&utm_campaign=v2.1#tabtop",
        "photo_count": 98,
        "menu_url": "https:\/\/www.zomato.com\/adelaide\/devour-cafe-patisserie-hilton\/menu?utm_source=api_basic_user&utm_medium=api&utm_campaign=v2.1&openSwipeBox=menu&showMinimal=1#tabtop",
        "featured_image": "https:\/\/b.zmtcdn.com\/data\/res_imagery\/16589175_RESTAURANT_1a56f8cf406e4d65f3fe74d6408cfc5d.jpg",
        "medio_provider": false,
        "has_online_delivery": 0,
        "is_delivering_now": 0,
        "store_type": "",
        "include_bogo_offers": true,
        "deeplink": "zomato:\/\/restaurant\/16589175",
        "is_table_reservation_supported": 0,
        "has_table_booking": 0,
        "events_url": "https:\/\/www.zomato.com\/adelaide\/devour-cafe-patisserie-hilton\/events#tabtop?utm_source=api_basic_user&utm_medium=api&utm_campaign=v2.1",
        "phone_numbers": "0411 536 343",
        "all_reviews": {
          "reviews": [
            {
              "review": []
            },
            {
              "review": []
            },
            {
              "review": []
            },
            {
              "review": []
            },
            {
              "review": []
            }
          ]
        },
        "establishment": [
          "Caf\u00e9"
        ],
        "establishment_types": []
      }
    },
    {
      "restaurant": {
        "R": {
          "res_id": 16587722,
          "is_grocery_store": false,
          "has_menu_status": {
            "delivery": -1,
            "takeaway": -1
          }
        },
        "apikey": "c1d331ff7e4dcfb200d33fa7efb9b184",
        "id": "16587722",
        "name": "The Ghan Kebab House",
        "url": "https:\/\/www.zomato.com\/adelaide\/the-ghan-kebab-house-blair-athol?utm_source=api_basic_user&utm_medium=api&utm_campaign=v2.1",
        "location": {
          "address": "364 Prospect Road, Kilburn",
          "locality": "Prospect Road, Blair Athol",
          "city": "Adelaide",
          "city_id": 297,
          "latitude": "-34.8658944444",
          "longitude": "138.5925138889",
          "zipcode": "5084",
          "country_id": 14,
          "locality_verbose": "Prospect Road, Blair Athol, Adelaide, SA"
        },
        "switch_to_order_menu": 0,
        "cuisines": "Middle Eastern, Afghan",
        "timings": "12 Noon to 10 PM (Mon-Sun)",
        "average_cost_for_two": 50,
        "price_range": 2,
        "currency": "$",
        "highlights": [
          "Takeaway Available",
          "Dinner",
          "Delivery",
          "Lunch",
          "Indoor Seating"
        ],
        "offers": [],
        "opentable_support": 0,
        "is_zomato_book_res": 0,
        "mezzo_provider": "OTHER",
        "is_book_form_web_view": 0,
        "book_form_web_view_url": "",
        "book_again_url": "",
        "thumb": "https:\/\/b.zmtcdn.com\/data\/res_imagery\/16587722_RESTAURANT_133e287e2e4c1b3af9ae05482305dcf5.jpg?fit=around%7C200%3A200&crop=200%3A200%3B%2A%2C%2A",
        "user_rating": {
          "aggregate_rating": "4.5",
          "rating_text": "Excellent",
          "rating_color": "3F7E00",
          "rating_obj": {
            "title": {
              "text": "4.5"
            },
            "bg_color": {
              "type": "lime",
              "tint": "700"
            }
          },
          "votes": 177
        },
        "all_reviews_count": 73,
        "photos_url": "https:\/\/www.zomato.com\/adelaide\/the-ghan-kebab-house-blair-athol\/photos?utm_source=api_basic_user&utm_medium=api&utm_campaign=v2.1#tabtop",
        "photo_count": 60,
        "menu_url": "https:\/\/www.zomato.com\/adelaide\/the-ghan-kebab-house-blair-athol\/menu?utm_source=api_basic_user&utm_medium=api&utm_campaign=v2.1&openSwipeBox=menu&showMinimal=1#tabtop",
        "featured_image": "https:\/\/b.zmtcdn.com\/data\/res_imagery\/16587722_RESTAURANT_133e287e2e4c1b3af9ae05482305dcf5.jpg",
        "medio_provider": false,
        "has_online_delivery": 0,
        "is_delivering_now": 0,
        "store_type": "",
        "include_bogo_offers": true,
        "deeplink": "zomato:\/\/restaurant\/16587722",
        "is_table_reservation_supported": 0,
        "has_table_booking": 0,
        "events_url": "https:\/\/www.zomato.com\/adelaide\/the-ghan-kebab-house-blair-athol\/events#tabtop?utm_source=api_basic_user&utm_medium=api&utm_campaign=v2.1",
        "phone_numbers": "(08) 8262 4042",
        "all_reviews": {
          "reviews": [
            {
              "review": []
            },
            {
              "review": []
            },
            {
              "review": []
            },
            {
              "review": []
            },
            {
              "review": []
            }
          ]
        },
        "establishment": [
          "Casual Dining"
        ],
        "establishment_types": []
      }
    },
    {
      "restaurant": {
        "R": {
          "res_id": 18235651,
          "is_grocery_store": false,
          "has_menu_status": {
            "delivery": -1,
            "takeaway": -1
          }
        },
        "apikey": "c1d331ff7e4dcfb200d33fa7efb9b184",
        "id": "18235651",
        "name": "Jamface by Poh",
        "url": "https:\/\/www.zomato.com\/adelaide\/jamface-by-poh-city-centre?utm_source=api_basic_user&utm_medium=api&utm_campaign=v2.1",
        "location": {
          "address": "Stall 28-29, Adelaide Central Markets, Adelaide",
          "locality": "City Centre",
          "city": "Adelaide",
          "city_id": 297,
          "latitude": "34.9295326000",
          "longitude": "138.5951123000",
          "zipcode": "",
          "country_id": 14,
          "locality_verbose": "City Centre"
        },
        "switch_to_order_menu": 0,
        "cuisines": "Bakery, Coffee and Tea, Cafe Food",
        "timings": "Closed (Mon, Wed, Sun), 7 AM to 5:30 PM (Tue, Thu), 7 AM to 9 PM (Fri),7 AM to 3 PM (Sat)",
        "average_cost_for_two": 30,
        "price_range": 2,
        "currency": "$",
        "highlights": [
          "Lunch",
          "Cash",
          "Debit Card",
          "Takeaway Available",
          "Breakfast",
          "No Alcohol Available",
          "Credit Card",
          "Kid Friendly",
          "Gluten Free Options",
          "Desserts and Bakes",
          "Indoor Seating"
        ],
        "offers": [],
        "opentable_support": 0,
        "is_zomato_book_res": 0,
        "mezzo_provider": "OTHER",
        "is_book_form_web_view": 0,
        "book_form_web_view_url": "",
        "book_again_url": "",
        "thumb": "https:\/\/b.zmtcdn.com\/data\/res_imagery\/18235651_RESTAURANT_dc9880f5bfe7ac634e3a9ed6c3e050f6.jpg?fit=around%7C200%3A200&crop=200%3A200%3B%2A%2C%2A",
        "user_rating": {
          "aggregate_rating": "4.0",
          "rating_text": "Very Good",
          "rating_color": "5BA829",
          "rating_obj": {
            "title": {
              "text": "4.0"
            },
            "bg_color": {
              "type": "lime",
              "tint": "600"
            }
          },
          "votes": 97
        },
        "all_reviews_count": 63,
        "photos_url": "https:\/\/www.zomato.com\/adelaide\/jamface-by-poh-city-centre\/photos?utm_source=api_basic_user&utm_medium=api&utm_campaign=v2.1#tabtop",
        "photo_count": 153,
        "menu_url": "https:\/\/www.zomato.com\/adelaide\/jamface-by-poh-city-centre\/menu?utm_source=api_basic_user&utm_medium=api&utm_campaign=v2.1&openSwipeBox=menu&showMinimal=1#tabtop",
        "featured_image": "https:\/\/b.zmtcdn.com\/data\/res_imagery\/18235651_RESTAURANT_dc9880f5bfe7ac634e3a9ed6c3e050f6.jpg?output-format=webp",
        "medio_provider": false,
        "has_online_delivery": 0,
        "is_delivering_now": 0,
        "store_type": "",
        "include_bogo_offers": true,
        "deeplink": "zomato:\/\/restaurant\/18235651",
        "is_table_reservation_supported": 0,
        "has_table_booking": 0,
        "events_url": "https:\/\/www.zomato.com\/adelaide\/jamface-by-poh-city-centre\/events#tabtop?utm_source=api_basic_user&utm_medium=api&utm_campaign=v2.1",
        "phone_numbers": "0433 815 137",
        "all_reviews": {
          "reviews": [
            {
              "review": []
            },
            {
              "review": []
            },
            {
              "review": []
            },
            {
              "review": []
            },
            {
              "review": []
            }
          ]
        },
        "establishment": [
          "Caf\u00e9"
        ],
        "establishment_types": []
      }
    },
    {
      "restaurant": {
        "R": {
          "res_id": 16587692,
          "is_grocery_store": false,
          "has_menu_status": {
            "delivery": -1,
            "takeaway": -1
          }
        },
        "apikey": "c1d331ff7e4dcfb200d33fa7efb9b184",
        "id": "16587692",
        "name": "Cafe Komodo",
        "url": "https:\/\/www.zomato.com\/adelaide\/cafe-komodo-prospect?utm_source=api_basic_user&utm_medium=api&utm_campaign=v2.1",
        "location": {
          "address": "118 Prospect Road, Prospect",
          "locality": "Prospect Road, Prospect",
          "city": "Adelaide",
          "city_id": 297,
          "latitude": "-34.8870194444",
          "longitude": "138.5935833333",
          "zipcode": "5082",
          "country_id": 14,
          "locality_verbose": "Prospect Road, Prospect, Adelaide, SA"
        },
        "switch_to_order_menu": 0,
        "cuisines": "Coffee and Tea, Cafe Food",
        "timings": "9 AM to 4 PM (Mon, Tue, Wed, Thu, Sat, Sun), 9 AM to 12 Midnight (Fri)",
        "average_cost_for_two": 70,
        "price_range": 3,
        "currency": "$",
        "highlights": [
          "Credit Card",
          "No Alcohol Available",
          "Cash",
          "Debit Card",
          "Takeaway Available",
          "Breakfast",
          "Lunch",
          "Live Music",
          "Outdoor Seating",
          "Kid Friendly",
          "Smoking Area",
          "Wifi",
          "Gluten Free Options",
          "Vegetarian Friendly",
          "Indoor Seating",
          "Wheelchair Accessible",
          "Vegan Options"
        ],
        "offers": [],
        "opentable_support": 0,
        "is_zomato_book_res": 0,
        "mezzo_provider": "OTHER",
        "is_book_form_web_view": 0,
        "book_form_web_view_url": "",
        "book_again_url": "",
        "thumb": "https:\/\/b.zmtcdn.com\/data\/res_imagery\/16587692_RESTAURANT_9a8c844b406e51e2fedbebd8c5e79320_c.jpg?fit=around%7C200%3A200&crop=200%3A200%3B%2A%2C%2A",
        "user_rating": {
          "aggregate_rating": "4.2",
          "rating_text": "Very Good",
          "rating_color": "5BA829",
          "rating_obj": {
            "title": {
              "text": "4.2"
            },
            "bg_color": {
              "type": "lime",
              "tint": "700"
            }
          },
          "votes": 215
        },
        "all_reviews_count": 76,
        "photos_url": "https:\/\/www.zomato.com\/adelaide\/cafe-komodo-prospect\/photos?utm_source=api_basic_user&utm_medium=api&utm_campaign=v2.1#tabtop",
        "photo_count": 42,
        "menu_url": "https:\/\/www.zomato.com\/adelaide\/cafe-komodo-prospect\/menu?utm_source=api_basic_user&utm_medium=api&utm_campaign=v2.1&openSwipeBox=menu&showMinimal=1#tabtop",
        "featured_image": "https:\/\/b.zmtcdn.com\/data\/res_imagery\/16587692_RESTAURANT_9a8c844b406e51e2fedbebd8c5e79320_c.jpg",
        "medio_provider": false,
        "has_online_delivery": 0,
        "is_delivering_now": 0,
        "store_type": "",
        "include_bogo_offers": true,
        "deeplink": "zomato:\/\/restaurant\/16587692",
        "is_table_reservation_supported": 0,
        "has_table_booking": 0,
        "events_url": "https:\/\/www.zomato.com\/adelaide\/cafe-komodo-prospect\/events#tabtop?utm_source=api_basic_user&utm_medium=api&utm_campaign=v2.1",
        "phone_numbers": "(08) 8344 7448",
        "all_reviews": {
          "reviews": [
            {
              "review": []
            },
            {
              "review": []
            },
            {
              "review": []
            },
            {
              "review": []
            },
            {
              "review": []
            }
          ]
        },
        "establishment": [
          "Caf\u00e9"
        ],
        "establishment_types": []
      }
    },
    {
      "restaurant": {
        "R": {
          "res_id": 16587002,
          "is_grocery_store": false,
          "has_menu_status": {
            "delivery": -1,
            "takeaway": -1
          }
        },
        "apikey": "c1d331ff7e4dcfb200d33fa7efb9b184",
        "id": "16587002",
        "name": "Ky Chow",
        "url": "https:\/\/www.zomato.com\/adelaide\/ky-chow-city-centre?utm_source=api_basic_user&utm_medium=api&utm_campaign=v2.1",
        "location": {
          "address": "27 Gouger Street, Adelaide, City Centre, Adelaide",
          "locality": "Gouger Street, City Centre",
          "city": "Adelaide",
          "city_id": 297,
          "latitude": "-34.9303470000",
          "longitude": "138.5982510000",
          "zipcode": "5000",
          "country_id": 14,
          "locality_verbose": "Gouger Street, City Centre, Adelaide, SA"
        },
        "switch_to_order_menu": 0,
        "cuisines": "Chinese",
        "timings": "12 Noon to 10 PM (Mon-Thu),12 Noon to 12 Midnight (Fri),12 Noon to 11 PM (Sat),5 PM to 10 PM (Sun)",
        "average_cost_for_two": 60,
        "price_range": 3,
        "currency": "$",
        "highlights": [
          "Credit Card",
          "Dinner",
          "Takeaway Available",
          "Lunch",
          "Indoor Seating",
          "Vegetarian Friendly",
          "Fullbar",
          "Outdoor Seating",
          "Lunch Menu"
        ],
        "offers": [],
        "opentable_support": 0,
        "is_zomato_book_res": 0,
        "mezzo_provider": "OTHER",
        "is_book_form_web_view": 0,
        "book_form_web_view_url": "",
        "book_again_url": "",
        "thumb": "https:\/\/b.zmtcdn.com\/data\/res_imagery\/16587002_RESTAURANT_5ba003284da51d9901a37c78ae6221eb_c.jpg?fit=around%7C200%3A200&crop=200%3A200%3B%2A%2C%2A",
        "user_rating": {
          "aggregate_rating": "4.2",
          "rating_text": "Very Good",
          "rating_color": "5BA829",
          "rating_obj": {
            "title": {
              "text": "4.2"
            },
            "bg_color": {
              "type": "lime",
              "tint": "700"
            }
          },
          "votes": 268
        },
        "all_reviews_count": 87,
        "photos_url": "https:\/\/www.zomato.com\/adelaide\/ky-chow-city-centre\/photos?utm_source=api_basic_user&utm_medium=api&utm_campaign=v2.1#tabtop",
        "photo_count": 64,
        "menu_url": "https:\/\/www.zomato.com\/adelaide\/ky-chow-city-centre\/menu?utm_source=api_basic_user&utm_medium=api&utm_campaign=v2.1&openSwipeBox=menu&showMinimal=1#tabtop",
        "featured_image": "https:\/\/b.zmtcdn.com\/data\/res_imagery\/16587002_RESTAURANT_5ba003284da51d9901a37c78ae6221eb_c.jpg?output-format=webp",
        "medio_provider": false,
        "has_online_delivery": 0,
        "is_delivering_now": 0,
        "store_type": "",
        "include_bogo_offers": true,
        "deeplink": "zomato:\/\/restaurant\/16587002",
        "is_table_reservation_supported": 0,
        "has_table_booking": 0,
        "events_url": "https:\/\/www.zomato.com\/adelaide\/ky-chow-city-centre\/events#tabtop?utm_source=api_basic_user&utm_medium=api&utm_campaign=v2.1",
        "phone_numbers": "(08) 8221 5411",
        "all_reviews": {
          "reviews": [
            {
              "review": []
            },
            {
              "review": []
            },
            {
              "review": []
            },
            {
              "review": []
            },
            {
              "review": []
            }
          ]
        },
        "establishment": [
          "Casual Dining"
        ],
        "establishment_types": []
      }
    },
    {
      "restaurant": {
        "R": {
          "res_id": 16587795,
          "is_grocery_store": false,
          "has_menu_status": {
            "delivery": -1,
            "takeaway": -1
          }
        },
        "apikey": "c1d331ff7e4dcfb200d33fa7efb9b184",
        "id": "16587795",
        "name": "Waffle's Waffle & Coffee",
        "url": "https:\/\/www.zomato.com\/adelaide\/waffles-waffle-coffee-city-centre?utm_source=api_basic_user&utm_medium=api&utm_campaign=v2.1",
        "location": {
          "address": "Shop 2, 20 Leigh Street, Adelaide",
          "locality": "Leigh Street, City Centre",
          "city": "Adelaide",
          "city_id": 297,
          "latitude": "-34.9238250000",
          "longitude": "138.5976861111",
          "zipcode": "5000",
          "country_id": 14,
          "locality_verbose": "Leigh Street, City Centre, Adelaide, SA"
        },
        "switch_to_order_menu": 0,
        "cuisines": "Desserts, Coffee and Tea, Cafe Food",
        "timings": "7:30 AM to 6 PM (Mon),7:30 AM to 9 PM (Tue-Thu),7:30 AM to 10 PM (Fri),12 Noon to 6 PM (Sat),Closed (Sun)",
        "average_cost_for_two": 25,
        "price_range": 1,
        "currency": "$",
        "highlights": [
          "Cash",
          "Debit Card",
          "Lunch",
          "Credit Card",
          "Takeaway Available",
          "Breakfast",
          "No Alcohol Available",
          "Indoor Seating",
          "Vegetarian Friendly",
          "Desserts and Bakes",
          "Outdoor Seating"
        ],
        "offers": [],
        "opentable_support": 0,
        "is_zomato_book_res": 0,
        "mezzo_provider": "OTHER",
        "is_book_form_web_view": 0,
        "book_form_web_view_url": "",
        "book_again_url": "",
        "thumb": "https:\/\/b.zmtcdn.com\/data\/res_imagery\/16587795_RESTAURANT_83fb5a660da569e220ca844e9f035659.jpg?fit=around%7C200%3A200&crop=200%3A200%3B%2A%2C%2A",
        "user_rating": {
          "aggregate_rating": "4.1",
          "rating_text": "Very Good",
          "rating_color": "5BA829",
          "rating_obj": {
            "title": {
              "text": "4.1"
            },
            "bg_color": {
              "type": "lime",
              "tint": "700"
            }
          },
          "votes": 126
        },
        "all_reviews_count": 38,
        "photos_url": "https:\/\/www.zomato.com\/adelaide\/waffles-waffle-coffee-city-centre\/photos?utm_source=api_basic_user&utm_medium=api&utm_campaign=v2.1#tabtop",
        "photo_count": 74,
        "menu_url": "https:\/\/www.zomato.com\/adelaide\/waffles-waffle-coffee-city-centre\/menu?utm_source=api_basic_user&utm_medium=api&utm_campaign=v2.1&openSwipeBox=menu&showMinimal=1#tabtop",
        "featured_image": "https:\/\/b.zmtcdn.com\/data\/res_imagery\/16587795_RESTAURANT_83fb5a660da569e220ca844e9f035659.jpg?output-format=webp",
        "medio_provider": false,
        "has_online_delivery": 0,
        "is_delivering_now": 0,
        "store_type": "",
        "include_bogo_offers": true,
        "deeplink": "zomato:\/\/restaurant\/16587795",
        "is_table_reservation_supported": 0,
        "has_table_booking": 0,
        "events_url": "https:\/\/www.zomato.com\/adelaide\/waffles-waffle-coffee-city-centre\/events#tabtop?utm_source=api_basic_user&utm_medium=api&utm_campaign=v2.1",
        "phone_numbers": "(08) 8231 7677",
        "all_reviews": {
          "reviews": [
            {
              "review": []
            },
            {
              "review": []
            },
            {
              "review": []
            },
            {
              "review": []
            },
            {
              "review": []
            }
          ]
        },
        "establishment": [
          "Dessert Parlour"
        ],
        "establishment_types": []
      }
    },
    {
      "restaurant": {
        "R": {
          "res_id": 18152453,
          "is_grocery_store": false,
          "has_menu_status": {
            "delivery": -1,
            "takeaway": -1
          }
        },
        "apikey": "c1d331ff7e4dcfb200d33fa7efb9b184",
        "id": "18152453",
        "name": "C.R.E.A.M",
        "url": "https:\/\/www.zomato.com\/adelaide\/c-r-e-a-m-brighton?utm_source=api_basic_user&utm_medium=api&utm_campaign=v2.1",
        "location": {
          "address": "4\/49 Jetty Road, Brighton, Adelaide",
          "locality": "Jetty Road, Brighton",
          "city": "Adelaide",
          "city_id": 297,
          "latitude": "-35.0173453457",
          "longitude": "138.5164356977",
          "zipcode": "",
          "country_id": 14,
          "locality_verbose": "Jetty Road, Brighton, Adelaide, SA"
        },
        "switch_to_order_menu": 0,
        "cuisines": "Coffee and Tea, Cafe Food",
        "timings": "8 AM to 4 PM",
        "average_cost_for_two": 40,
        "price_range": 2,
        "currency": "$",
        "highlights": [
          "Credit Card",
          "No Alcohol Available",
          "Takeaway Available",
          "Breakfast",
          "Lunch",
          "Kid Friendly",
          "Gluten Free Options",
          "Vegetarian Friendly",
          "Indoor Seating",
          "Vegan Options"
        ],
        "offers": [],
        "opentable_support": 0,
        "is_zomato_book_res": 0,
        "mezzo_provider": "OTHER",
        "is_book_form_web_view": 0,
        "book_form_web_view_url": "",
        "book_again_url": "",
        "thumb": "https:\/\/b.zmtcdn.com\/data\/res_imagery\/18152453_RESTAURANT_02cf87e8cf859ac19ada693ba95274b2.jpg?fit=around%7C200%3A200&crop=200%3A200%3B%2A%2C%2A",
        "user_rating": {
          "aggregate_rating": "3.9",
          "rating_text": "Good",
          "rating_color": "9ACD32",
          "rating_obj": {
            "title": {
              "text": "3.9"
            },
            "bg_color": {
              "type": "lime",
              "tint": "600"
            }
          },
          "votes": 120
        },
        "all_reviews_count": 56,
        "photos_url": "https:\/\/www.zomato.com\/adelaide\/c-r-e-a-m-brighton\/photos?utm_source=api_basic_user&utm_medium=api&utm_campaign=v2.1#tabtop",
        "photo_count": 58,
        "menu_url": "https:\/\/www.zomato.com\/adelaide\/c-r-e-a-m-brighton\/menu?utm_source=api_basic_user&utm_medium=api&utm_campaign=v2.1&openSwipeBox=menu&showMinimal=1#tabtop",
        "featured_image": "https:\/\/b.zmtcdn.com\/data\/res_imagery\/18152453_RESTAURANT_02cf87e8cf859ac19ada693ba95274b2.jpg",
        "medio_provider": false,
        "has_online_delivery": 0,
        "is_delivering_now": 0,
        "store_type": "",
        "include_bogo_offers": true,
        "deeplink": "zomato:\/\/restaurant\/18152453",
        "is_table_reservation_supported": 0,
        "has_table_booking": 0,
        "events_url": "https:\/\/www.zomato.com\/adelaide\/c-r-e-a-m-brighton\/events#tabtop?utm_source=api_basic_user&utm_medium=api&utm_campaign=v2.1",
        "phone_numbers": "08 8298 3149",
        "all_reviews": {
          "reviews": [
            {
              "review": []
            },
            {
              "review": []
            },
            {
              "review": []
            },
            {
              "review": []
            },
            {
              "review": []
            }
          ]
        },
        "establishment": [
          "Caf\u00e9"
        ],
        "establishment_types": []
      }
    },
    {
      "restaurant": {
        "R": {
          "res_id": 16587892,
          "is_grocery_store": false,
          "has_menu_status": {
            "delivery": -1,
            "takeaway": -1
          }
        },
        "apikey": "c1d331ff7e4dcfb200d33fa7efb9b184",
        "id": "16587892",
        "name": "Chocolatree",
        "url": "https:\/\/www.zomato.com\/adelaide\/chocolatree-north-adelaide?utm_source=api_basic_user&utm_medium=api&utm_campaign=v2.1",
        "location": {
          "address": "25 O'Connell Street, North Adelaide",
          "locality": "O'connell Street, North Adelaide",
          "city": "Adelaide",
          "city_id": 297,
          "latitude": "-34.9082916667",
          "longitude": "138.5966805556",
          "zipcode": "5006",
          "country_id": 14,
          "locality_verbose": "O'connell Street, North Adelaide, Adelaide, SA"
        },
        "switch_to_order_menu": 0,
        "cuisines": "Desserts",
        "timings": "10 AM to 11 PM (Mon, Tue, Wed, Thu, Sun), 10 AM to 12 Midnight (Fri-Sat)",
        "average_cost_for_two": 35,
        "price_range": 2,
        "currency": "$",
        "highlights": [
          "Cash",
          "Debit Card",
          "Takeaway Available",
          "Breakfast",
          "No Alcohol Available",
          "Credit Card",
          "Lunch",
          "Indoor Seating",
          "Vegan Options",
          "Outdoor Seating",
          "Wheelchair Accessible",
          "Gluten Free Options",
          "Vegetarian Friendly",
          "Desserts and Bakes"
        ],
        "offers": [],
        "opentable_support": 0,
        "is_zomato_book_res": 0,
        "mezzo_provider": "OTHER",
        "is_book_form_web_view": 0,
        "book_form_web_view_url": "",
        "book_again_url": "",
        "thumb": "https:\/\/b.zmtcdn.com\/data\/res_imagery\/16587892_RESTAURANT_71c28c0c312cc0d320a27669a48e13f9_c.jpg?fit=around%7C200%3A200&crop=200%3A200%3B%2A%2C%2A",
        "user_rating": {
          "aggregate_rating": "3.7",
          "rating_text": "Good",
          "rating_color": "9ACD32",
          "rating_obj": {
            "title": {
              "text": "3.7"
            },
            "bg_color": {
              "type": "lime",
              "tint": "600"
            }
          },
          "votes": 252
        },
        "all_reviews_count": 116,
        "photos_url": "https:\/\/www.zomato.com\/adelaide\/chocolatree-north-adelaide\/photos?utm_source=api_basic_user&utm_medium=api&utm_campaign=v2.1#tabtop",
        "photo_count": 83,
        "menu_url": "https:\/\/www.zomato.com\/adelaide\/chocolatree-north-adelaide\/menu?utm_source=api_basic_user&utm_medium=api&utm_campaign=v2.1&openSwipeBox=menu&showMinimal=1#tabtop",
        "featured_image": "https:\/\/b.zmtcdn.com\/data\/res_imagery\/16587892_RESTAURANT_71c28c0c312cc0d320a27669a48e13f9_c.jpg",
        "medio_provider": false,
        "has_online_delivery": 0,
        "is_delivering_now": 0,
        "store_type": "",
        "include_bogo_offers": true,
        "deeplink": "zomato:\/\/restaurant\/16587892",
        "is_table_reservation_supported": 0,
        "has_table_booking": 0,
        "events_url": "https:\/\/www.zomato.com\/adelaide\/chocolatree-north-adelaide\/events#tabtop?utm_source=api_basic_user&utm_medium=api&utm_campaign=v2.1",
        "phone_numbers": "(08) 8367 0443",
        "all_reviews": {
          "reviews": [
            {
              "review": []
            },
            {
              "review": []
            },
            {
              "review": []
            },
            {
              "review": []
            },
            {
              "review": []
            }
          ]
        },
        "establishment": [
          "Dessert Parlour"
        ],
        "establishment_types": []
      }
    },
    {
      "restaurant": {
        "R": {
          "res_id": 16589555,
          "is_grocery_store": false,
          "has_menu_status": {
            "delivery": -1,
            "takeaway": -1
          }
        },
        "apikey": "c1d331ff7e4dcfb200d33fa7efb9b184",
        "id": "16589555",
        "name": "Sukhumvit Soi 38",
        "url": "https:\/\/www.zomato.com\/adelaide\/sukhumvit-soi--city-centre?utm_source=api_basic_user&utm_medium=api&utm_campaign=v2.1",
        "location": {
          "address": "54 Pulteney Street, Adelaide",
          "locality": "City Centre",
          "city": "Adelaide",
          "city_id": 297,
          "latitude": "-34.9231305721",
          "longitude": "138.6054790020",
          "zipcode": "5000",
          "country_id": 14,
          "locality_verbose": "City Centre"
        },
        "switch_to_order_menu": 0,
        "cuisines": "Thai",
        "timings": "11:30 AM to 2:30 PM, 5:30 PM to 9:30 PM (Mon-Thu),11:30 AM to 2:30 PM, 5:30 PM to 11 PM (Fri-Sat),Closed (Sun)",
        "average_cost_for_two": 90,
        "price_range": 3,
        "currency": "$",
        "highlights": [
          "Credit Card",
          "Takeaway Available",
          "Dinner",
          "Lunch",
          "Wheelchair Accessible",
          "Vegetarian Friendly",
          "Indoor Seating",
          "Wifi",
          "Vegan Options"
        ],
        "offers": [],
        "opentable_support": 0,
        "is_zomato_book_res": 0,
        "mezzo_provider": "OTHER",
        "is_book_form_web_view": 0,
        "book_form_web_view_url": "",
        "book_again_url": "",
        "thumb": "https:\/\/b.zmtcdn.com\/data\/res_imagery\/16589555_RESTAURANT_da515c2f540e46e407b02011b32392de.jpg?fit=around%7C200%3A200&crop=200%3A200%3B%2A%2C%2A",
        "user_rating": {
          "aggregate_rating": "4.2",
          "rating_text": "Very Good",
          "rating_color": "5BA829",
          "rating_obj": {
            "title": {
              "text": "4.2"
            },
            "bg_color": {
              "type": "lime",
              "tint": "700"
            }
          },
          "votes": 147
        },
        "all_reviews_count": 80,
        "photos_url": "https:\/\/www.zomato.com\/adelaide\/sukhumvit-soi--city-centre\/photos?utm_source=api_basic_user&utm_medium=api&utm_campaign=v2.1#tabtop",
        "photo_count": 92,
        "menu_url": "https:\/\/www.zomato.com\/adelaide\/sukhumvit-soi--city-centre\/menu?utm_source=api_basic_user&utm_medium=api&utm_campaign=v2.1&openSwipeBox=menu&showMinimal=1#tabtop",
        "featured_image": "https:\/\/b.zmtcdn.com\/data\/res_imagery\/16589555_RESTAURANT_da515c2f540e46e407b02011b32392de.jpg",
        "medio_provider": false,
        "has_online_delivery": 0,
        "is_delivering_now": 0,
        "store_type": "",
        "include_bogo_offers": true,
        "deeplink": "zomato:\/\/restaurant\/16589555",
        "is_table_reservation_supported": 0,
        "has_table_booking": 0,
        "events_url": "https:\/\/www.zomato.com\/adelaide\/sukhumvit-soi--city-centre\/events#tabtop?utm_source=api_basic_user&utm_medium=api&utm_campaign=v2.1",
        "phone_numbers": "(08) 8223 5472",
        "all_reviews": {
          "reviews": [
            {
              "review": []
            },
            {
              "review": []
            },
            {
              "review": []
            },
            {
              "review": []
            },
            {
              "review": []
            }
          ]
        },
        "establishment": [
          "Casual Dining"
        ],
        "establishment_types": []
      }
    },
    {
      "restaurant": {
        "R": {
          "res_id": 16587199,
          "is_grocery_store": false,
          "has_menu_status": {
            "delivery": -1,
            "takeaway": -1
          }
        },
        "apikey": "c1d331ff7e4dcfb200d33fa7efb9b184",
        "id": "16587199",
        "name": "Star House",
        "url": "https:\/\/www.zomato.com\/adelaide\/star-house-city-centre?utm_source=api_basic_user&utm_medium=api&utm_campaign=v2.1",
        "location": {
          "address": "39 Gouger Street, Adelaide",
          "locality": "Gouger Street, City Centre",
          "city": "Adelaide",
          "city_id": 297,
          "latitude": "-34.9301113576",
          "longitude": "138.5980449244",
          "zipcode": "5000",
          "country_id": 14,
          "locality_verbose": "Gouger Street, City Centre, Adelaide, SA"
        },
        "switch_to_order_menu": 0,
        "cuisines": "Chinese, Thai, Yum Cha",
        "timings": "11 AM to 3:30 PM, 5 PM to 10 PM (Mon-Fri),10:30 AM to 3:30 PM, 5 PM to 10 PM (Sat-Sun)",
        "average_cost_for_two": 60,
        "price_range": 3,
        "currency": "$",
        "highlights": [
          "Credit Card",
          "Lunch",
          "Takeaway Available",
          "Dinner",
          "Indoor Seating",
          "Vegetarian Friendly",
          "Outdoor Seating",
          "Fullbar"
        ],
        "offers": [],
        "opentable_support": 0,
        "is_zomato_book_res": 0,
        "mezzo_provider": "OTHER",
        "is_book_form_web_view": 0,
        "book_form_web_view_url": "",
        "book_again_url": "",
        "thumb": "https:\/\/b.zmtcdn.com\/data\/res_imagery\/16587199_RESTAURANT_e538abb842e203e12807686931d9da83_c.jpg?fit=around%7C200%3A200&crop=200%3A200%3B%2A%2C%2A",
        "user_rating": {
          "aggregate_rating": "4.0",
          "rating_text": "Very Good",
          "rating_color": "5BA829",
          "rating_obj": {
            "title": {
              "text": "4.0"
            },
            "bg_color": {
              "type": "lime",
              "tint": "600"
            }
          },
          "votes": 258
        },
        "all_reviews_count": 114,
        "photos_url": "https:\/\/www.zomato.com\/adelaide\/star-house-city-centre\/photos?utm_source=api_basic_user&utm_medium=api&utm_campaign=v2.1#tabtop",
        "photo_count": 74,
        "menu_url": "https:\/\/www.zomato.com\/adelaide\/star-house-city-centre\/menu?utm_source=api_basic_user&utm_medium=api&utm_campaign=v2.1&openSwipeBox=menu&showMinimal=1#tabtop",
        "featured_image": "https:\/\/b.zmtcdn.com\/data\/res_imagery\/16587199_RESTAURANT_e538abb842e203e12807686931d9da83_c.jpg",
        "medio_provider": false,
        "has_online_delivery": 0,
        "is_delivering_now": 0,
        "store_type": "",
        "include_bogo_offers": true,
        "deeplink": "zomato:\/\/restaurant\/16587199",
        "is_table_reservation_supported": 0,
        "has_table_booking": 0,
        "events_url": "https:\/\/www.zomato.com\/adelaide\/star-house-city-centre\/events#tabtop?utm_source=api_basic_user&utm_medium=api&utm_campaign=v2.1",
        "phone_numbers": "(08) 8221 6303",
        "all_reviews": {
          "reviews": [
            {
              "review": []
            },
            {
              "review": []
            },
            {
              "review": []
            },
            {
              "review": []
            },
            {
              "review": []
            }
          ]
        },
        "establishment": [
          "Casual Dining"
        ],
        "establishment_types": []
      }
    },
    {
      "restaurant": {
        "R": {
          "res_id": 16587330,
          "is_grocery_store": false,
          "has_menu_status": {
            "delivery": -1,
            "takeaway": -1
          }
        },
        "apikey": "c1d331ff7e4dcfb200d33fa7efb9b184",
        "id": "16587330",
        "name": "Elephant Walk",
        "url": "https:\/\/www.zomato.com\/adelaide\/elephant-walk-north-adelaide?utm_source=api_basic_user&utm_medium=api&utm_campaign=v2.1",
        "location": {
          "address": "76 Melbourne Street, North Adelaide",
          "locality": "Melbourne Street, North Adelaide",
          "city": "Adelaide",
          "city_id": 297,
          "latitude": "-34.9062942516",
          "longitude": "138.6083868518",
          "zipcode": "5006",
          "country_id": 14,
          "locality_verbose": "Melbourne Street, North Adelaide, Adelaide, SA"
        },
        "switch_to_order_menu": 0,
        "cuisines": "Desserts",
        "timings": "7:30 PM to 10 PM",
        "average_cost_for_two": 40,
        "price_range": 2,
        "currency": "$",
        "highlights": [
          "Credit Card",
          "Cash",
          "Takeaway Available",
          "Indoor Seating",
          "Desserts and Bakes"
        ],
        "offers": [],
        "opentable_support": 0,
        "is_zomato_book_res": 0,
        "mezzo_provider": "OTHER",
        "is_book_form_web_view": 0,
        "book_form_web_view_url": "",
        "book_again_url": "",
        "thumb": "https:\/\/b.zmtcdn.com\/data\/res_imagery\/16587330_RESTAURANT_2185f68ab58b0c659c7158e25089fcc5.jpg?fit=around%7C200%3A200&crop=200%3A200%3B%2A%2C%2A",
        "user_rating": {
          "aggregate_rating": "3.5",
          "rating_text": "Good",
          "rating_color": "9ACD32",
          "rating_obj": {
            "title": {
              "text": "3.5"
            },
            "bg_color": {
              "type": "lime",
              "tint": "500"
            }
          },
          "votes": 282
        },
        "all_reviews_count": 70,
        "photos_url": "https:\/\/www.zomato.com\/adelaide\/elephant-walk-north-adelaide\/photos?utm_source=api_basic_user&utm_medium=api&utm_campaign=v2.1#tabtop",
        "photo_count": 28,
        "menu_url": "https:\/\/www.zomato.com\/adelaide\/elephant-walk-north-adelaide\/menu?utm_source=api_basic_user&utm_medium=api&utm_campaign=v2.1&openSwipeBox=menu&showMinimal=1#tabtop",
        "featured_image": "https:\/\/b.zmtcdn.com\/data\/res_imagery\/16587330_RESTAURANT_2185f68ab58b0c659c7158e25089fcc5.jpg",
        "medio_provider": false,
        "has_online_delivery": 0,
        "is_delivering_now": 0,
        "store_type": "",
        "include_bogo_offers": true,
        "deeplink": "zomato:\/\/restaurant\/16587330",
        "is_table_reservation_supported": 0,
        "has_table_booking": 0,
        "events_url": "https:\/\/www.zomato.com\/adelaide\/elephant-walk-north-adelaide\/events#tabtop?utm_source=api_basic_user&utm_medium=api&utm_campaign=v2.1",
        "phone_numbers": "08 7080 7247",
        "all_reviews": {
          "reviews": [
            {
              "review": []
            },
            {
              "review": []
            },
            {
              "review": []
            },
            {
              "review": []
            },
            {
              "review": []
            }
          ]
        },
        "establishment": [
          "Dessert Parlour"
        ],
        "establishment_types": []
      }
    },
    {
      "restaurant": {
        "R": {
          "res_id": 16587397,
          "is_grocery_store": false,
          "has_menu_status": {
            "delivery": -1,
            "takeaway": -1
          }
        },
        "apikey": "c1d331ff7e4dcfb200d33fa7efb9b184",
        "id": "16587397",
        "name": "BBQ City Restaurant",
        "url": "https:\/\/www.zomato.com\/adelaide\/bbq-city-restaurant-city-centre?utm_source=api_basic_user&utm_medium=api&utm_campaign=v2.1",
        "location": {
          "address": "84 Gouger Street, Adelaide",
          "locality": "Gouger Street, City Centre",
          "city": "Adelaide",
          "city_id": 297,
          "latitude": "-34.9302078392",
          "longitude": "138.5961492732",
          "zipcode": "5000",
          "country_id": 14,
          "locality_verbose": "Gouger Street, City Centre, Adelaide, SA"
        },
        "switch_to_order_menu": 0,
        "cuisines": "BBQ, Chinese",
        "timings": "11 AM to 11 PM (Mon, Wed, Thu, Fri, Sat, Sun), 11 AM to 10 PM (Tue)",
        "average_cost_for_two": 55,
        "price_range": 2,
        "currency": "$",
        "highlights": [
          "Credit Card",
          "Dinner",
          "Takeaway Available",
          "Lunch",
          "Indoor Seating",
          "Vegetarian Friendly",
          "Outdoor Seating"
        ],
        "offers": [],
        "opentable_support": 0,
        "is_zomato_book_res": 0,
        "mezzo_provider": "OTHER",
        "is_book_form_web_view": 0,
        "book_form_web_view_url": "",
        "book_again_url": "",
        "thumb": "https:\/\/b.zmtcdn.com\/data\/res_imagery\/16587397_RESTAURANT_d7339d73a17153eb0950845d3fe30f0f_c.jpg?fit=around%7C200%3A200&crop=200%3A200%3B%2A%2C%2A",
        "user_rating": {
          "aggregate_rating": "3.3",
          "rating_text": "Average",
          "rating_color": "CDD614",
          "rating_obj": {
            "title": {
              "text": "3.3"
            },
            "bg_color": {
              "type": "lime",
              "tint": "500"
            }
          },
          "votes": 314
        },
        "all_reviews_count": 145,
        "photos_url": "https:\/\/www.zomato.com\/adelaide\/bbq-city-restaurant-city-centre\/photos?utm_source=api_basic_user&utm_medium=api&utm_campaign=v2.1#tabtop",
        "photo_count": 55,
        "menu_url": "https:\/\/www.zomato.com\/adelaide\/bbq-city-restaurant-city-centre\/menu?utm_source=api_basic_user&utm_medium=api&utm_campaign=v2.1&openSwipeBox=menu&showMinimal=1#tabtop",
        "featured_image": "https:\/\/b.zmtcdn.com\/data\/res_imagery\/16587397_RESTAURANT_d7339d73a17153eb0950845d3fe30f0f_c.jpg?output-format=webp",
        "medio_provider": false,
        "has_online_delivery": 0,
        "is_delivering_now": 0,
        "store_type": "",
        "include_bogo_offers": true,
        "deeplink": "zomato:\/\/restaurant\/16587397",
        "is_table_reservation_supported": 0,
        "has_table_booking": 0,
        "events_url": "https:\/\/www.zomato.com\/adelaide\/bbq-city-restaurant-city-centre\/events#tabtop?utm_source=api_basic_user&utm_medium=api&utm_campaign=v2.1",
        "phone_numbers": "(08) 8212 8299",
        "all_reviews": {
          "reviews": [
            {
              "review": []
            },
            {
              "review": []
            },
            {
              "review": []
            },
            {
              "review": []
            },
            {
              "review": []
            }
          ]
        },
        "establishment": [
          "Casual Dining"
        ],
        "establishment_types": []
      }
    }
  ]
}
